my_own_package/__init__.py
First_package_Carlo_Catanuso-0.2.0.dist-info/METADATA
First_package_Carlo_Catanuso-0.2.0.dist-info/WHEEL
First_package_Carlo_Catanuso-0.2.0.dist-info/top_level.txt
First_package_Carlo_Catanuso-0.2.0.dist-info/RECORD
