Metadata-Version: 2.1
Name: First-package-Carlo-Catanuso
Version: 0.2.0
Summary: My first package
Author: Carlo
Author-email: catanusoc@yahoo.com
